circleso/__init__.py
circleso/client.py
pycircleso-0.0.1.dist-info/LICENSE
pycircleso-0.0.1.dist-info/WHEEL
pycircleso-0.0.1.dist-info/METADATA
pycircleso-0.0.1.dist-info/RECORD
