Metadata-Version: 2.1
Name: pycircleso
Version: 0.0.1
Summary: 
License: Apache
Author: Philip James
Author-email: phildini@phildini.net
Requires-Python: >=3.9,<4.0
Classifier: License :: Other/Proprietary License
Classifier: Programming Language :: Python :: 3
Classifier: Programming Language :: Python :: 3.9
Classifier: Programming Language :: Python :: 3.10
Requires-Dist: requests (>=2.28.1,<3.0.0)
